oauthenticator/__init__.py
oauthenticator/_version.py
oauthenticator/auth0.py
oauthenticator/awscognito.py
oauthenticator/azuread.py
oauthenticator/azureadb2c.py
oauthenticator/bitbucket.py
oauthenticator/cilogon.py
oauthenticator/common.py
oauthenticator/generic.py
oauthenticator/github.py
oauthenticator/gitlab.py
oauthenticator/globus.py
oauthenticator/google.py
oauthenticator/mediawiki.py
oauthenticator/oauth2.py
oauthenticator/okpy.py
oauthenticator/openshift.py
oauthenticator/traitlets.py
oauthenticator/yandex.py
oauthenticator/schemas/cilogon-schema.yaml
oauthenticator/tests/__init__.py
oauthenticator/tests/conftest.py
oauthenticator/tests/mocks.py
oauthenticator/tests/test_auth0.py
oauthenticator/tests/test_azuread.py
oauthenticator/tests/test_bitbucket.py
oauthenticator/tests/test_cilogon.py
oauthenticator/tests/test_generic.py
oauthenticator/tests/test_github.py
oauthenticator/tests/test_gitlab.py
oauthenticator/tests/test_globus.py
oauthenticator/tests/test_google.py
oauthenticator/tests/test_mediawiki.py
oauthenticator/tests/test_oauth2.py
oauthenticator/tests/test_okpy.py
oauthenticator/tests/test_openshift.py
oauthenticator_plus-15.1.3.dist-info/LICENSE
oauthenticator_plus-15.1.3.dist-info/METADATA
oauthenticator_plus-15.1.3.dist-info/WHEEL
oauthenticator_plus-15.1.3.dist-info/entry_points.txt
oauthenticator_plus-15.1.3.dist-info/top_level.txt
oauthenticator_plus-15.1.3.dist-info/RECORD
