Metadata-Version: 2.1
Name: oauthenticator-plus
Version: 15.1.3
Summary: OAuthenticator: Authenticate JupyterHub users with common OAuth providers
Home-page: https://jupyter.org
Author: Jupyter Development Team
Author-email: jupyter@googlegroups.com
License: BSD
Keywords: Interactive,Interpreter,Shell,Web
Platform: Linux
Platform: Mac OS X
Classifier: Intended Audience :: Developers
Classifier: Intended Audience :: System Administrators
Classifier: Intended Audience :: Science/Research
Classifier: License :: OSI Approved :: BSD License
Classifier: Programming Language :: Python
Classifier: Programming Language :: Python :: 3
Requires-Python: >=3.6
License-File: LICENSE
Requires-Dist: jsonschema
Requires-Dist: jupyterhub (>=1.2)
Requires-Dist: requests
Requires-Dist: ruamel.yaml
Provides-Extra: googlegroups
Requires-Dist: google-api-python-client ; extra == 'googlegroups'
Requires-Dist: google-auth-oauthlib ; extra == 'googlegroups'
